cloudinary_storage/__init__.py
cloudinary_storage/app_settings.py
cloudinary_storage/apps.py
cloudinary_storage/helpers.py
cloudinary_storage/storage.py
cloudinary_storage/validators.py
cloudinary_storage/management/__init__.py
cloudinary_storage/management/commands/__init__.py
cloudinary_storage/management/commands/collectstatic.py
cloudinary_storage/management/commands/deleteorphanedmedia.py
cloudinary_storage/management/commands/deleteredundantstatic.py
cloudinary_storage/templatetags/__init__.py
cloudinary_storage/templatetags/cloudinary_static.py
django_cloudinary_storage_thelab-0.2.3.dist-info/LICENSE
django_cloudinary_storage_thelab-0.2.3.dist-info/METADATA
django_cloudinary_storage_thelab-0.2.3.dist-info/WHEEL
django_cloudinary_storage_thelab-0.2.3.dist-info/top_level.txt
django_cloudinary_storage_thelab-0.2.3.dist-info/RECORD
